genome_mcp/__init__.py
genome_mcp/__main__.py
genome_mcp/main.py
genome_mcp/analysis/__init__.py
genome_mcp/analysis/kegg_analysis.py
genome_mcp/analysis/simple_stats.py
genome_mcp/core/__init__.py
genome_mcp/core/clients.py
genome_mcp/core/ensembl_client.py
genome_mcp/core/errors.py
genome_mcp/core/evolution_tools.py
genome_mcp/core/query_executor.py
genome_mcp/core/query_parser.py
genome_mcp/core/tools.py
genome_mcp/core/types.py
genome_mcp/core/validation.py
genome_mcp/utils/__init__.py
genome_mcp/utils/validation.py
genome_mcp-0.2.6.dist-info/METADATA
genome_mcp-0.2.6.dist-info/WHEEL
genome_mcp-0.2.6.dist-info/entry_points.txt
genome_mcp-0.2.6.dist-info/top_level.txt
genome_mcp-0.2.6.dist-info/RECORD
