Metadata-Version: 2.4
Name: genome-mcp
Version: 0.2.6
Summary: Genome MCP server - 优化版本：智能基因组数据访问
Author-email: gqy20 <qingyu_ge@foxmail.com>
Maintainer-email: gqy20 <qingyu_ge@foxmail.com>
License-Expression: MIT
Project-URL: Homepage, https://github.com/gqy20/genome-mcp
Project-URL: Repository, https://github.com/gqy20/genome-mcp
Project-URL: Documentation, https://github.com/gqy20/genome-mcp#readme
Project-URL: Bug Tracker, https://github.com/gqy20/genome-mcp/issues
Keywords: mcp,genomics,bioinformatics,ncbi,gene
Classifier: Development Status :: 4 - Beta
Classifier: Intended Audience :: Science/Research
Classifier: Operating System :: OS Independent
Classifier: Programming Language :: Python :: 3
Classifier: Programming Language :: Python :: 3.11
Classifier: Programming Language :: Python :: 3.12
Classifier: Topic :: Scientific/Engineering :: Bio-Informatics
Requires-Python: >=3.11
Requires-Dist: aiohttp>=3.8.0
Requires-Dist: fastmcp>=2.0.0
Requires-Dist: typing-extensions>=4.0.0
Provides-Extra: dev
Requires-Dist: pytest>=7.0.0; extra == "dev"
Requires-Dist: pytest-asyncio>=0.21.0; extra == "dev"
Requires-Dist: black>=23.0.0; extra == "dev"
Requires-Dist: isort>=5.12.0; extra == "dev"
Requires-Dist: ruff>=0.1.0; extra == "dev"
Provides-Extra: test
Requires-Dist: pytest>=7.0.0; extra == "test"
Requires-Dist: pytest-asyncio>=0.21.0; extra == "test"
Requires-Dist: pytest-cov>=4.0.0; extra == "test"
